{
  "name": "Google SecOps Marketplace",
  "entries": {
    "2025-06-18": [
      {
        "kind": "Changed",
        "content": "**Google Chronicle**: Version 60.0\n\n* Updated risk score handling in the following connector:\n\n  + **Google Chronicle - Alerts Connector**"
      },
      {
        "kind": "Changed",
        "content": "**Microsoft Teams**: Version 27.0\n\n* **Integration**: Refactored the code to work with updated API."
      }
    ],
    "2025-06-11": [
      {
        "kind": "Feature",
        "content": "New **Akamai** integration"
      },
      {
        "kind": "Feature",
        "content": "New **Google Threat Intelligence** integration"
      },
      {
        "kind": "Changed",
        "content": "**Darktrace**: Version 18.0\n\n* Added ability to filter model breaches by priority in the following connector:\n\n  + **Darktrace - Model Breaches Connector**"
      },
      {
        "kind": "Changed",
        "content": "Refactored the code to work with updated API in the following integrations:\n\n* **Exchange**: Version 113.0\n* **ServiceNow**: Version 57.0\n* **Microsoft Graph Mail Delegated**: Version 5.0"
      }
    ],
    "2025-06-04": [
      {
        "kind": "Changed",
        "content": "Refactored the code to work with updated API in the following integrations:\n\n* **BMC Remedy ITSM**: Version 8.0\n* **Gmail**: Version 3.0\n* **Google Cloud API**: Version 5.0\n* **Microsoft Graph Mail**: Version 27.0\n* **Service Desk Plus V3**: Version 6.0\n* **Vertex AI**: Version 2.0"
      },
      {
        "kind": "Changed",
        "content": "**Google Chronicle**: Version 59.0\n\n* Updated the API root to be configurable in IDE in the following connector:\n  + **Google Chronicle - Chronicle Alerts Connector**"
      },
      {
        "kind": "Changed",
        "content": "**Nmap**: Version 2.0\n\n* Updated JSON Result structure in the following action:\n  + **Scan Entities**"
      },
      {
        "kind": "Changed",
        "content": "**Vertex AI**: Version 2.0\n\n* Fixed non-Google models that weren't working"
      }
    ]
  }
}