{
  "name": "Cloud API Registry",
  "entries": {
    "2025-12-10": [
      {
        "kind": "Announcement",
        "content": "Cloud API Registry is available in\n[Preview](https://cloud.google.com/products/#product-launch-stages).\n\nCloud API Registry lets you discover, govern, use, and monitor\nModel Context Protocol (MCP) servers and tools provided by Google, or by your\norganization through Apigee API hub. For more information, see the\n[Cloud API Registry overview](https://docs.cloud.google.com/api-registry/docs/overview).",
        "summary": {
          "title": "API Registry Now in Preview",
          "summary": "Cloud API Registry, a new service for discovering, governing, and using API servers and tools, is now available in preview. It supports both Google-provided and your organization's APIs through Apigee API hub, offering enhanced API management capabilities."
        }
      }
    ]
  }
}